minidatabase/WebMDB.py
minidatabase/__init__.py
minidatabase/minidb.py
minidatabase-1.7.1.dist-info/LICENSE.txt
minidatabase-1.7.1.dist-info/METADATA
minidatabase-1.7.1.dist-info/WHEEL
minidatabase-1.7.1.dist-info/entry_points.txt
minidatabase-1.7.1.dist-info/top_level.txt
minidatabase-1.7.1.dist-info/RECORD
