Metadata-Version: 2.1
Name: minidatabase
Version: 1.7.1
Summary: A tiny database system based on  python dictionary.
Home-page: http://osdn.xyz
Author: HansenL
Author-email: hansenl@foxmail.com
License: GNU GENERAL PUBLIC LICENSE
Platform: all
Classifier: Intended Audience :: Developers
Classifier: Operating System :: OS Independent
Classifier: Natural Language :: Chinese (Simplified)
Classifier: Programming Language :: Python
Classifier: Programming Language :: Python :: 3
Classifier: Programming Language :: Python :: 3.5
Classifier: Programming Language :: Python :: 3.6
Classifier: Programming Language :: Python :: 3.7
Classifier: Programming Language :: Python :: 3.8
Classifier: Topic :: Software Development :: Libraries
License-File: LICENSE.txt
Requires-Dist: requests
Requires-Dist: flask
